ChangeLog.txt
LICENSE.txt
MANIFEST.in
README.rst
setup.cfg
setup.py
django_supervisor.egg-info/PKG-INFO
django_supervisor.egg-info/SOURCES.txt
django_supervisor.egg-info/dependency_links.txt
django_supervisor.egg-info/requires.txt
django_supervisor.egg-info/top_level.txt
djsupervisor/__init__.py
djsupervisor/config.py
djsupervisor/events.py
djsupervisor/models.py
djsupervisor/tests.py
djsupervisor/management/__init__.py
djsupervisor/management/commands/__init__.py
djsupervisor/management/commands/supervisor.py
djsupervisor/templatetags/__init__.py
djsupervisor/templatetags/djsupervisor_tags.py