Metadata-Version: 1.1
Name: django-supervisor
Version: 0.3.2
Summary: easy integration between djangocl and supervisord
Home-page: http://github.com/rfk/django-supervisor
Author: Ryan Kelly
Author-email: ryan@rfk.id.au
License: MIT
Keywords: django supervisord process
Platform: UNKNOWN
Classifier: Programming Language :: Python
Classifier: Programming Language :: Python :: 2
Classifier: License :: OSI Approved
Classifier: License :: OSI Approved :: MIT License
Classifier: Development Status :: 3 - Alpha
Classifier: Intended Audience :: Developers
